{
    "name": "gpop",
    "title": "jQuery Gallery Pop",
    "description": "jQuery plugin for image galleries with pop up effect.",
    "keywords": [
        "gallery",
        "popup",
        "images"
    ],
    "version": "0.2.0",
    "author": {
        "name": "Vanamco GmbH",
        "url": "http://www.vanamco.com/humans.txt"
    },
    "licenses": [
        {
            "type": "MIT",
            "url": "http://github.com/vnmc/jquery.gpop/blob/master/LICENSE"
        }
    ],
    "bugs": "https://github.com/vnmc/jquery.gpop/issues",
    "homepage": "http://www.vanamco.com/jquery.gpop/demo.html",
    "docs": "https://github.com/vnmc/jquery.gpop/blob/master/README.md",
    "download": "https://github.com/vnmc/jquery.gpop/",
    "dependencies": {
        "jquery": ">=1.7"
    }
}